{
  "data": {
    "article": {},
    "attachments": {},
    "author_id": "1510447851507261445",
    "conversation_id": "1923258887014150542",
    "created_at": "2025-05-16T13:15:16.000Z",
    "edit_controls": {
      "editable_until": "2025-05-16T14:15:16.000Z",
      "edits_remaining": 5,
      "is_edit_eligible": false
    },
    "edit_history_tweet_ids": [
      "1923366642601340945"
    ],
    "entities": {
      "mentions": [
        {
          "end": 12,
          "id": "1351490794809528323",
          "start": 0,
          "username": "dldreamyear"
        }
      ]
    },
    "geo": {},
    "id": "1923366642601340945",
    "in_reply_to_user_id": "1351490794809528323",
    "lang": "zh",
    "note_tweet": {
      "entities": {}
    },
    "possibly_sensitive": false,
    "public_metrics": {
      "bookmark_count": 0,
      "impression_count": 0,
      "like_count": 0,
      "quote_count": 0,
      "reply_count": 0,
      "retweet_count": 0
    },
    "referenced_tweets": [
      {
        "id": "1923358310364856544",
        "type": "replied_to"
      }
    ],
    "reply_settings": "everyone",
    "text": "@dldreamyear 搜过膝袜加长就可以了喵 应该都差不多"
  },
  "includes": {
    "tweets": [
      {
        "article": {},
        "attachments": {},
        "author_id": "1510447851507261445",
        "conversation_id": "1923258887014150542",
        "created_at": "2025-05-16T13:15:16.000Z",
        "edit_controls": {
          "editable_until": "2025-05-16T14:15:16.000Z",
          "edits_remaining": 5,
          "is_edit_eligible": false
        },
        "edit_history_tweet_ids": [
          "1923366642601340945"
        ],
        "entities": {
          "mentions": [
            {
              "end": 12,
              "id": "1351490794809528323",
              "start": 0,
              "username": "dldreamyear"
            }
          ]
        },
        "geo": {},
        "id": "1923366642601340945",
        "in_reply_to_user_id": "1351490794809528323",
        "lang": "zh",
        "note_tweet": {
          "entities": {}
        },
        "possibly_sensitive": false,
        "public_metrics": {
          "bookmark_count": 0,
          "impression_count": 0,
          "like_count": 0,
          "quote_count": 0,
          "reply_count": 0,
          "retweet_count": 0
        },
        "referenced_tweets": [
          {
            "id": "1923358310364856544",
            "type": "replied_to"
          }
        ],
        "reply_settings": "everyone",
        "text": "@dldreamyear 搜过膝袜加长就可以了喵 应该都差不多"
      },
      {
        "article": {},
        "attachments": {},
        "author_id": "1351490794809528323",
        "conversation_id": "1923258887014150542",
        "created_at": "2025-05-16T12:42:10.000Z",
        "edit_controls": {
          "editable_until": "2025-05-16T13:42:10.000Z",
          "edits_remaining": 5,
          "is_edit_eligible": false
        },
        "edit_history_tweet_ids": [
          "1923358310364856544"
        ],
        "entities": {
          "mentions": [
            {
              "end": 11,
              "id": "1510447851507261445",
              "start": 0,
              "username": "LanziiLove"
            }
          ]
        },
        "geo": {},
        "id": "1923358310364856544",
        "in_reply_to_user_id": "1510447851507261445",
        "lang": "zh",
        "note_tweet": {
          "entities": {}
        },
        "possibly_sensitive": false,
        "public_metrics": {
          "bookmark_count": 0,
          "impression_count": 16,
          "like_count": 0,
          "quote_count": 0,
          "reply_count": 1,
          "retweet_count": 0
        },
        "referenced_tweets": [
          {
            "id": "1923258887014150542",
            "type": "replied_to"
          }
        ],
        "reply_settings": "everyone",
        "text": "@LanziiLove 哪家的袜子呀，求推荐"
      }
    ],
    "users": [
      {
        "created_at": "2022-04-03T02:43:33.000Z",
        "description": "19岁 不含🍬🇨🇳男娘 可以叫咱小雫哦w｜已有男朋友@dexy0306 他叫然然～（他超可爱！） 是纯爱哦｜理智爱国 不见证 ｜纯清水 无黄无福利 不接任何业务 私信骚扰的等着挨骂吧｜无门槛 同好可酌情扩列｜备用小号@hosh1no_sh1zuku｜全网同名 只有B站/X/抖音有号 其他均为假冒",
        "entities": {
          "description": {
            "mentions": [
              {
                "end": 35,
                "start": 26,
                "username": "dexy0306"
              },
              {
                "end": 124,
                "start": 108,
                "username": "hosh1no_sh1zuku"
              }
            ]
          }
        },
        "id": "1510447851507261445",
        "location": "然然的怀里",
        "name": "星野雫丶Shizuku✨",
        "profile_image_url": "https://pbs.twimg.com/profile_images/1911751252460888064/Emjcd7cS_normal.jpg",
        "protected": false,
        "public_metrics": {
          "followers_count": 14382,
          "following_count": 719,
          "like_count": 414,
          "listed_count": 39,
          "media_count": 155,
          "tweet_count": 729
        },
        "username": "LanziiLove",
        "verified": false
      },
      {
        "created_at": "2021-01-19T11:24:57.000Z",
        "description": "喜欢芭蕾靴，脚镣，Lolita以及一切可爱的事物。\n周末随缘更新，一个人自娱自乐，顺便拍点照片。\n身高185/体重65，东北人在湖南工作。\nXP广泛，但很多没有搭子尝试不了。",
        "id": "1351490794809528323",
        "name": "浮生若梦",
        "profile_image_url": "https://pbs.twimg.com/profile_images/1873547892595863552/DXQP-SJP_normal.jpg",
        "protected": false,
        "public_metrics": {
          "followers_count": 2890,
          "following_count": 39,
          "like_count": 7,
          "listed_count": 7,
          "media_count": 42,
          "tweet_count": 271
        },
        "username": "dldreamyear",
        "verified": false
      }
    ]
  }
}