{
  "data": {
    "article": {},
    "attachments": {},
    "author_id": "1510447851507261445",
    "conversation_id": "2004137545701945544",
    "created_at": "2025-12-26T10:05:04.000Z",
    "edit_controls": {
      "editable_until": "2025-12-26T11:05:04.000Z",
      "edits_remaining": 5,
      "is_edit_eligible": false
    },
    "edit_history_tweet_ids": [
      "2004493659581075812"
    ],
    "entities": {
      "mentions": [
        {
          "end": 12,
          "id": "1337760768696201216",
          "start": 0,
          "username": "BalloonSama"
        },
        {
          "end": 27,
          "id": "1450640115085111300",
          "start": 13,
          "username": "PowerfulAuraX"
        }
      ]
    },
    "geo": {},
    "id": "2004493659581075812",
    "in_reply_to_user_id": "1337760768696201216",
    "lang": "zh",
    "note_tweet": {
      "entities": {}
    },
    "possibly_sensitive": false,
    "public_metrics": {
      "bookmark_count": 0,
      "impression_count": 0,
      "like_count": 0,
      "quote_count": 0,
      "reply_count": 0,
      "retweet_count": 0
    },
    "referenced_tweets": [
      {
        "id": "2004353409051513161",
        "type": "replied_to"
      }
    ],
    "reply_settings": "everyone",
    "text": "@BalloonSama @PowerfulAuraX 傻逼"
  },
  "includes": {
    "media": [
      {
        "height": 2048,
        "media_key": "3_2004353405322412032",
        "public_metrics": {},
        "type": "photo",
        "url": "https://pbs.twimg.com/media/G9DkzXiWQAAwVzu.jpg",
        "width": 922
      },
      {
        "height": 1136,
        "media_key": "3_2004353405322477569",
        "public_metrics": {},
        "type": "photo",
        "url": "https://pbs.twimg.com/media/G9DkzXiXQAE45Oe.jpg",
        "width": 600
      }
    ],
    "tweets": [
      {
        "article": {},
        "attachments": {},
        "author_id": "1510447851507261445",
        "conversation_id": "2004137545701945544",
        "created_at": "2025-12-26T10:05:04.000Z",
        "edit_controls": {
          "editable_until": "2025-12-26T11:05:04.000Z",
          "edits_remaining": 5,
          "is_edit_eligible": false
        },
        "edit_history_tweet_ids": [
          "2004493659581075812"
        ],
        "entities": {
          "mentions": [
            {
              "end": 12,
              "id": "1337760768696201216",
              "start": 0,
              "username": "BalloonSama"
            },
            {
              "end": 27,
              "id": "1450640115085111300",
              "start": 13,
              "username": "PowerfulAuraX"
            }
          ]
        },
        "geo": {},
        "id": "2004493659581075812",
        "in_reply_to_user_id": "1337760768696201216",
        "lang": "zh",
        "note_tweet": {
          "entities": {}
        },
        "possibly_sensitive": false,
        "public_metrics": {
          "bookmark_count": 0,
          "impression_count": 0,
          "like_count": 0,
          "quote_count": 0,
          "reply_count": 0,
          "retweet_count": 0
        },
        "referenced_tweets": [
          {
            "id": "2004353409051513161",
            "type": "replied_to"
          }
        ],
        "reply_settings": "everyone",
        "text": "@BalloonSama @PowerfulAuraX 傻逼"
      },
      {
        "article": {},
        "attachments": {
          "media_keys": [
            "3_2004353405322412032",
            "3_2004353405322477569"
          ]
        },
        "author_id": "1337760768696201216",
        "context_annotations": [
          {
            "domain": {
              "description": "Categories within Brand Verticals that narrow down the scope of Brands",
              "id": "46",
              "name": "Business Taxonomy"
            },
            "entity": {
              "description": "Brands, companies, advertisers and every non-person handle with the profit intent related to offline and online games such as gaming consoles, tabletop games, video game publishers",
              "id": "1557696940178935808",
              "name": "Gaming Business"
            }
          }
        ],
        "conversation_id": "2004137545701945544",
        "created_at": "2025-12-26T00:47:46.000Z",
        "edit_controls": {
          "editable_until": "2025-12-26T01:47:46.000Z",
          "edits_remaining": 5,
          "is_edit_eligible": false
        },
        "edit_history_tweet_ids": [
          "2004353409051513161"
        ],
        "entities": {
          "mentions": [
            {
              "end": 14,
              "id": "1450640115085111300",
              "start": 0,
              "username": "PowerfulAuraX"
            }
          ],
          "urls": [
            {
              "display_url": "pic.x.com/fXNtPivITJ",
              "end": 102,
              "expanded_url": "https://x.com/BalloonSama/status/2004353409051513161/photo/1",
              "media_key": "3_2004353405322412032",
              "start": 79,
              "url": "https://t.co/fXNtPivITJ"
            },
            {
              "display_url": "pic.x.com/fXNtPivITJ",
              "end": 102,
              "expanded_url": "https://x.com/BalloonSama/status/2004353409051513161/photo/1",
              "media_key": "3_2004353405322477569",
              "start": 79,
              "url": "https://t.co/fXNtPivITJ"
            }
          ]
        },
        "geo": {},
        "id": "2004353409051513161",
        "in_reply_to_user_id": "1450640115085111300",
        "lang": "en",
        "note_tweet": {
          "entities": {}
        },
        "possibly_sensitive": false,
        "public_metrics": {
          "bookmark_count": 0,
          "impression_count": 1572,
          "like_count": 29,
          "quote_count": 0,
          "reply_count": 6,
          "retweet_count": 0
        },
        "referenced_tweets": [
          {
            "id": "2004137545701945544",
            "type": "replied_to"
          }
        ],
        "reply_settings": "everyone",
        "text": "@PowerfulAuraX This cat is from Chinese media and he got abused hella hard btw https://t.co/fXNtPivITJ"
      }
    ],
    "users": [
      {
        "created_at": "2022-04-03T02:43:33.000Z",
        "description": "05年🇨🇳//纯清水 非跨无药不是男娘是男的 照片高P 上网纯娱乐//男友@Dexy0306//高考674分做题区//爱好编曲 画画 3DCG cos//985大二计算机科学与技术第二学位数学//B站6.6万粉丝同名//无差别block所有见证傻狗//音乐&绘画作品 音乐平台&Pixiv @LanziiLove",
        "entities": {
          "description": {
            "mentions": [
              {
                "end": 46,
                "start": 37,
                "username": "Dexy0306"
              },
              {
                "end": 156,
                "start": 145,
                "username": "LanziiLove"
              }
            ]
          }
        },
        "id": "1510447851507261445",
        "location": "世界和平☮️World Peace",
        "name": "星野雫丶Shizuku✨",
        "pinned_tweet_id": "1946772875698110774",
        "profile_image_url": "https://pbs.twimg.com/profile_images/1981816759138033665/JwkHNEt6_normal.jpg",
        "protected": false,
        "public_metrics": {
          "followers_count": 22335,
          "following_count": 979,
          "like_count": 1596,
          "listed_count": 69,
          "media_count": 348,
          "tweet_count": 1768
        },
        "username": "LanziiLove",
        "verified": false
      },
      {
        "created_at": "2020-12-12T14:06:45.000Z",
        "description": "i am so fucking dead || B Prospector  B ToyMerchant C sculptor",
        "id": "1337760768696201216",
        "location": "United States",
        "name": "爱是治愈百病的良药",
        "pinned_tweet_id": "1942049071641854319",
        "profile_image_url": "https://pbs.twimg.com/profile_images/1942083514213576704/sxrDTOQm_normal.jpg",
        "protected": false,
        "public_metrics": {
          "followers_count": 16,
          "following_count": 33,
          "like_count": 2771,
          "listed_count": 0,
          "media_count": 44,
          "tweet_count": 449
        },
        "username": "BalloonSama",
        "verified": false
      },
      {
        "created_at": "2021-10-20T01:49:02.000Z",
        "description": "these cats are powerful. Bringing the best on your feed. Dm for credit/removal.",
        "id": "1450640115085111300",
        "name": "cats with powerful aura",
        "pinned_tweet_id": "2004046949486665808",
        "profile_image_url": "https://pbs.twimg.com/profile_images/1945936553642995712/1aKLVi1l_normal.jpg",
        "protected": false,
        "public_metrics": {
          "followers_count": 268381,
          "following_count": 10443,
          "like_count": 1699,
          "listed_count": 991,
          "media_count": 5140,
          "tweet_count": 6421
        },
        "username": "PowerfulAuraX",
        "verified": true
      }
    ]
  }
}