{
  "data": {
    "article": {},
    "attachments": {},
    "author_id": "1510447851507261445",
    "conversation_id": "1923565401998532781",
    "created_at": "2025-05-17T02:56:06.000Z",
    "edit_controls": {
      "editable_until": "2025-05-17T03:56:06.000Z",
      "edits_remaining": 5,
      "is_edit_eligible": false
    },
    "edit_history_tweet_ids": [
      "1923573210400030981"
    ],
    "entities": {
      "mentions": [
        {
          "end": 12,
          "id": "1681716872415440896",
          "start": 0,
          "username": "Kirayoumiya"
        }
      ]
    },
    "geo": {},
    "id": "1923573210400030981",
    "in_reply_to_user_id": "1681716872415440896",
    "lang": "zh",
    "note_tweet": {
      "entities": {}
    },
    "possibly_sensitive": false,
    "public_metrics": {
      "bookmark_count": 0,
      "impression_count": 0,
      "like_count": 0,
      "quote_count": 0,
      "reply_count": 0,
      "retweet_count": 0
    },
    "referenced_tweets": [
      {
        "id": "1923573043269644483",
        "type": "replied_to"
      }
    ],
    "reply_settings": "everyone",
    "text": "@Kirayoumiya 超绝10cm防水台wwww\n\n不过崴一下人估计就没了wwww"
  },
  "includes": {
    "tweets": [
      {
        "article": {},
        "attachments": {},
        "author_id": "1510447851507261445",
        "conversation_id": "1923565401998532781",
        "created_at": "2025-05-17T02:56:06.000Z",
        "edit_controls": {
          "editable_until": "2025-05-17T03:56:06.000Z",
          "edits_remaining": 5,
          "is_edit_eligible": false
        },
        "edit_history_tweet_ids": [
          "1923573210400030981"
        ],
        "entities": {
          "mentions": [
            {
              "end": 12,
              "id": "1681716872415440896",
              "start": 0,
              "username": "Kirayoumiya"
            }
          ]
        },
        "geo": {},
        "id": "1923573210400030981",
        "in_reply_to_user_id": "1681716872415440896",
        "lang": "zh",
        "note_tweet": {
          "entities": {}
        },
        "possibly_sensitive": false,
        "public_metrics": {
          "bookmark_count": 0,
          "impression_count": 0,
          "like_count": 0,
          "quote_count": 0,
          "reply_count": 0,
          "retweet_count": 0
        },
        "referenced_tweets": [
          {
            "id": "1923573043269644483",
            "type": "replied_to"
          }
        ],
        "reply_settings": "everyone",
        "text": "@Kirayoumiya 超绝10cm防水台wwww\n\n不过崴一下人估计就没了wwww"
      },
      {
        "article": {},
        "attachments": {},
        "author_id": "1681716872415440896",
        "conversation_id": "1923565401998532781",
        "created_at": "2025-05-17T02:55:26.000Z",
        "edit_controls": {
          "editable_until": "2025-05-17T03:55:26.000Z",
          "edits_remaining": 5,
          "is_edit_eligible": false
        },
        "edit_history_tweet_ids": [
          "1923573043269644483"
        ],
        "entities": {
          "mentions": [
            {
              "end": 11,
              "id": "1510447851507261445",
              "start": 0,
              "username": "LanziiLove"
            }
          ]
        },
        "geo": {},
        "id": "1923573043269644483",
        "in_reply_to_user_id": "1510447851507261445",
        "lang": "zh",
        "note_tweet": {
          "entities": {}
        },
        "possibly_sensitive": false,
        "public_metrics": {
          "bookmark_count": 0,
          "impression_count": 2,
          "like_count": 0,
          "quote_count": 0,
          "reply_count": 1,
          "retweet_count": 0
        },
        "referenced_tweets": [
          {
            "id": "1923565401998532781",
            "type": "replied_to"
          }
        ],
        "reply_settings": "everyone",
        "text": "@LanziiLove 这鞋子好有力量感\n感觉能一脚把我踢死（"
      }
    ],
    "users": [
      {
        "created_at": "2022-04-03T02:43:33.000Z",
        "description": "19岁 不含🍬🇨🇳男娘 可以叫咱小雫哦w｜已有男朋友@dexy0306 他叫然然～（他超可爱！） 是纯爱哦｜理智爱国 不见证 ｜纯清水 无黄无福利 不接任何业务 私信骚扰的等着挨骂吧｜无门槛 同好可酌情扩列｜备用小号@hosh1no_sh1zuku｜全网同名 只有B站/X/抖音有号 其他均为假冒",
        "entities": {
          "description": {
            "mentions": [
              {
                "end": 35,
                "start": 26,
                "username": "dexy0306"
              },
              {
                "end": 124,
                "start": 108,
                "username": "hosh1no_sh1zuku"
              }
            ]
          }
        },
        "id": "1510447851507261445",
        "location": "然然的怀里",
        "name": "星野雫丶Shizuku✨",
        "profile_image_url": "https://pbs.twimg.com/profile_images/1911751252460888064/Emjcd7cS_normal.jpg",
        "protected": false,
        "public_metrics": {
          "followers_count": 14493,
          "following_count": 719,
          "like_count": 416,
          "listed_count": 39,
          "media_count": 157,
          "tweet_count": 740
        },
        "username": "LanziiLove",
        "verified": false
      },
      {
        "created_at": "2023-07-19T17:25:30.000Z",
        "description": "可以把这里当树洞哦  头像来自@PetitPoissonXY",
        "entities": {
          "description": {
            "mentions": [
              {
                "end": 30,
                "start": 15,
                "username": "PetitPoissonXY"
              }
            ]
          },
          "url": {
            "urls": [
              {
                "display_url": "ngl.link/kirayoumiya1",
                "end": 23,
                "expanded_url": "https://ngl.link/kirayoumiya1",
                "start": 0,
                "url": "https://t.co/M01koGznLh"
              }
            ]
          }
        },
        "id": "1681716872415440896",
        "name": "Kirayoumiya",
        "pinned_tweet_id": "1880843039654211614",
        "profile_image_url": "https://pbs.twimg.com/profile_images/1909534662948687872/vW4fhq51_normal.jpg",
        "protected": false,
        "public_metrics": {
          "followers_count": 317,
          "following_count": 800,
          "like_count": 10517,
          "listed_count": 2,
          "media_count": 289,
          "tweet_count": 9137
        },
        "url": "https://t.co/M01koGznLh",
        "username": "Kirayoumiya",
        "verified": false
      }
    ]
  }
}