{
  "data": {
    "article": {},
    "attachments": {},
    "author_id": "1510447851507261445",
    "conversation_id": "1924495321109024839",
    "created_at": "2025-05-19T16:27:18.000Z",
    "edit_controls": {
      "editable_until": "2025-05-19T17:27:18.000Z",
      "edits_remaining": 5,
      "is_edit_eligible": false
    },
    "edit_history_tweet_ids": [
      "1924502131828224464"
    ],
    "entities": {
      "mentions": [
        {
          "end": 12,
          "id": "1767040816986656768",
          "start": 0,
          "username": "MeviuslX_Xl"
        },
        {
          "end": 28,
          "id": "1615404813856178176",
          "start": 13,
          "username": "Lovemostmevius"
        }
      ]
    },
    "geo": {},
    "id": "1924502131828224464",
    "in_reply_to_user_id": "1767040816986656768",
    "lang": "und",
    "note_tweet": {
      "entities": {}
    },
    "possibly_sensitive": false,
    "public_metrics": {
      "bookmark_count": 0,
      "impression_count": 0,
      "like_count": 0,
      "quote_count": 0,
      "reply_count": 0,
      "retweet_count": 0
    },
    "referenced_tweets": [
      {
        "id": "1924495321109024839",
        "type": "replied_to"
      }
    ],
    "reply_settings": "everyone",
    "text": "@MeviuslX_Xl @Lovemostmevius 999999！"
  },
  "includes": {
    "tweets": [
      {
        "article": {},
        "attachments": {},
        "author_id": "1510447851507261445",
        "conversation_id": "1924495321109024839",
        "created_at": "2025-05-19T16:27:18.000Z",
        "edit_controls": {
          "editable_until": "2025-05-19T17:27:18.000Z",
          "edits_remaining": 5,
          "is_edit_eligible": false
        },
        "edit_history_tweet_ids": [
          "1924502131828224464"
        ],
        "entities": {
          "mentions": [
            {
              "end": 12,
              "id": "1767040816986656768",
              "start": 0,
              "username": "MeviuslX_Xl"
            },
            {
              "end": 28,
              "id": "1615404813856178176",
              "start": 13,
              "username": "Lovemostmevius"
            }
          ]
        },
        "geo": {},
        "id": "1924502131828224464",
        "in_reply_to_user_id": "1767040816986656768",
        "lang": "und",
        "note_tweet": {
          "entities": {}
        },
        "possibly_sensitive": false,
        "public_metrics": {
          "bookmark_count": 0,
          "impression_count": 0,
          "like_count": 0,
          "quote_count": 0,
          "reply_count": 0,
          "retweet_count": 0
        },
        "referenced_tweets": [
          {
            "id": "1924495321109024839",
            "type": "replied_to"
          }
        ],
        "reply_settings": "everyone",
        "text": "@MeviuslX_Xl @Lovemostmevius 999999！"
      },
      {
        "article": {},
        "attachments": {},
        "author_id": "1767040816986656768",
        "conversation_id": "1924495321109024839",
        "created_at": "2025-05-19T16:00:14.000Z",
        "edit_controls": {
          "editable_until": "2025-05-19T17:00:14.000Z",
          "edits_remaining": 5,
          "is_edit_eligible": true
        },
        "edit_history_tweet_ids": [
          "1924495321109024839"
        ],
        "entities": {
          "mentions": [
            {
              "end": 71,
              "id": "1615404813856178176",
              "start": 56,
              "username": "Lovemostmevius"
            }
          ]
        },
        "geo": {},
        "id": "1924495321109024839",
        "lang": "zh",
        "note_tweet": {
          "entities": {}
        },
        "possibly_sensitive": false,
        "public_metrics": {
          "bookmark_count": 0,
          "impression_count": 115,
          "like_count": 9,
          "quote_count": 0,
          "reply_count": 3,
          "retweet_count": 0
        },
        "reply_settings": "everyone",
        "text": "老公老公！！！最亲爱的老公～主人～520快乐！！！小梅最最最最！！！最爱你啦！！！mua～小梅要和你涩涩！！！\n@Lovemostmevius \n小梅要！！！\n嫁给你！！！\n做你永远的妻子！！！"
      }
    ],
    "users": [
      {
        "created_at": "2022-04-03T02:43:33.000Z",
        "description": "19岁 无🍬🇨🇳男娘 可以叫咱小雫哦w｜最爱的人是妈妈和老公｜男朋友@dexy0306 他叫然然～（他超可爱！） 是纯爱哦｜理智爱国 不见证 ｜纯清水 无黄无福利 无任何业务 私信骚扰等着挨骂吧｜无门槛 同好可酌情扩列｜备用小号@hosh1no_sh1zuku｜全网同名 只有B站/X/抖音有号 其他均为假冒",
        "entities": {
          "description": {
            "mentions": [
              {
                "end": 43,
                "start": 34,
                "username": "dexy0306"
              },
              {
                "end": 130,
                "start": 114,
                "username": "hosh1no_sh1zuku"
              }
            ]
          }
        },
        "id": "1510447851507261445",
        "location": "然然的怀里",
        "name": "星野雫丶Shizuku✨",
        "profile_image_url": "https://pbs.twimg.com/profile_images/1911751252460888064/Emjcd7cS_normal.jpg",
        "protected": false,
        "public_metrics": {
          "followers_count": 14699,
          "following_count": 719,
          "like_count": 442,
          "listed_count": 40,
          "media_count": 169,
          "tweet_count": 785
        },
        "username": "LanziiLove",
        "verified": false
      },
      {
        "created_at": "2024-03-11T04:12:28.000Z",
        "description": "这里是持证含糖の小魅魔小梅哦～｜HRT：2024.04.05｜家暴党｜猫猫@Mevius01XXX｜小梅的主人+老公 +比翼鸟+未婚夫@Lovemostmevius ｜妈咪 @miya051223｜小梅最重要的朋友们@yanyan2567 、@Ming_xm2、 @XCCQAQ 、@LingYi13380｜提问箱⬇️",
        "entities": {
          "description": {
            "mentions": [
              {
                "end": 49,
                "start": 37,
                "username": "Mevius01XXX"
              },
              {
                "end": 82,
                "start": 67,
                "username": "Lovemostmevius"
              },
              {
                "end": 98,
                "start": 87,
                "username": "miya051223"
              },
              {
                "end": 119,
                "start": 108,
                "username": "yanyan2567"
              },
              {
                "end": 130,
                "start": 121,
                "username": "Ming_xm2"
              },
              {
                "end": 139,
                "start": 132,
                "username": "XCCQAQ"
              },
              {
                "end": 153,
                "start": 141,
                "username": "LingYi13380"
              }
            ]
          },
          "url": {
            "urls": [
              {
                "display_url": "ngl.link/MeviuslX_Xl843…",
                "end": 23,
                "expanded_url": "https://ngl.link/MeviuslX_Xl84305",
                "start": 0,
                "url": "https://t.co/raPAD3yFdi"
              }
            ]
          }
        },
        "id": "1767040816986656768",
        "location": "往世乐土",
        "name": "ℳℯ𝓋𝒾𝓊𝓈",
        "pinned_tweet_id": "1910008859642716254",
        "profile_image_url": "https://pbs.twimg.com/profile_images/1899853858014466048/8KeK6HES_normal.jpg",
        "protected": false,
        "public_metrics": {
          "followers_count": 13231,
          "following_count": 1083,
          "like_count": 16438,
          "listed_count": 28,
          "media_count": 956,
          "tweet_count": 7479
        },
        "url": "https://t.co/raPAD3yFdi",
        "username": "MeviuslX_Xl",
        "verified": true
      },
      {
        "created_at": "2023-01-17T17:45:10.000Z",
        "description": "MTX |是狐娘～|大四在读 | 兔兔的唯一+主人+对象+女朋友+比翼鸟+一直爱着守护陪伴的下去人+另一半+老婆+darling～+女王殿下 @MeviuslX_Xl｜大兔兔/姐姐@miya051223 |  如果需要帮助的地方可以私信哦～",
        "entities": {
          "description": {
            "mentions": [
              {
                "end": 83,
                "start": 71,
                "username": "MeviuslX_Xl"
              },
              {
                "end": 101,
                "start": 90,
                "username": "miya051223"
              }
            ]
          }
        },
        "id": "1615404813856178176",
        "location": "ℳℯ𝓋𝒾𝓊𝓈 的心",
        "name": "MXT",
        "pinned_tweet_id": "1911630089382666727",
        "profile_image_url": "https://pbs.twimg.com/profile_images/1873761540312313856/ltyDX-7Y_normal.jpg",
        "protected": false,
        "public_metrics": {
          "followers_count": 3278,
          "following_count": 934,
          "like_count": 17980,
          "listed_count": 4,
          "media_count": 40,
          "tweet_count": 5879
        },
        "username": "Lovemostmevius",
        "verified": false
      }
    ]
  }
}