{
  "data": {
    "article": {},
    "attachments": {},
    "author_id": "1510447851507261445",
    "conversation_id": "2049048427313746179",
    "created_at": "2026-04-28T09:34:28.000Z",
    "edit_controls": {
      "editable_until": "2026-04-28T10:34:28.000Z",
      "edits_remaining": 5,
      "is_edit_eligible": false
    },
    "edit_history_tweet_ids": [
      "2049059664839790715"
    ],
    "entities": {
      "mentions": [
        {
          "end": 12,
          "id": "1767040816986656768",
          "start": 0,
          "username": "MeviuslX_Xl"
        }
      ]
    },
    "geo": {},
    "id": "2049059664839790715",
    "in_reply_to_user_id": "1767040816986656768",
    "lang": "zh",
    "note_tweet": {
      "entities": {}
    },
    "possibly_sensitive": false,
    "public_metrics": {
      "bookmark_count": 0,
      "impression_count": 0,
      "like_count": 0,
      "quote_count": 0,
      "reply_count": 0,
      "retweet_count": 0
    },
    "referenced_tweets": [
      {
        "id": "2049048427313746179",
        "type": "replied_to"
      }
    ],
    "reply_settings": "everyone",
    "text": "@MeviuslX_Xl 摸摸 不用管那些sb\n爱自己做好自己的确最重要\n小梅加油！"
  },
  "includes": {
    "tweets": [
      {
        "article": {},
        "attachments": {},
        "author_id": "1510447851507261445",
        "conversation_id": "2049048427313746179",
        "created_at": "2026-04-28T09:34:28.000Z",
        "edit_controls": {
          "editable_until": "2026-04-28T10:34:28.000Z",
          "edits_remaining": 5,
          "is_edit_eligible": false
        },
        "edit_history_tweet_ids": [
          "2049059664839790715"
        ],
        "entities": {
          "mentions": [
            {
              "end": 12,
              "id": "1767040816986656768",
              "start": 0,
              "username": "MeviuslX_Xl"
            }
          ]
        },
        "geo": {},
        "id": "2049059664839790715",
        "in_reply_to_user_id": "1767040816986656768",
        "lang": "zh",
        "note_tweet": {
          "entities": {}
        },
        "possibly_sensitive": false,
        "public_metrics": {
          "bookmark_count": 0,
          "impression_count": 0,
          "like_count": 0,
          "quote_count": 0,
          "reply_count": 0,
          "retweet_count": 0
        },
        "referenced_tweets": [
          {
            "id": "2049048427313746179",
            "type": "replied_to"
          }
        ],
        "reply_settings": "everyone",
        "text": "@MeviuslX_Xl 摸摸 不用管那些sb\n爱自己做好自己的确最重要\n小梅加油！"
      },
      {
        "article": {},
        "attachments": {},
        "author_id": "1767040816986656768",
        "conversation_id": "2049048427313746179",
        "created_at": "2026-04-28T08:49:49.000Z",
        "edit_controls": {
          "editable_until": "2026-04-28T09:49:49.000Z",
          "edits_remaining": 5,
          "is_edit_eligible": true
        },
        "edit_history_tweet_ids": [
          "2049048427313746179"
        ],
        "entities": {
          "urls": [
            {
              "display_url": "x.com/meviuslx_xl/st…",
              "end": 166,
              "expanded_url": "https://twitter.com/meviuslx_xl/status/2049046973068820873",
              "start": 143,
              "url": "https://t.co/9x7kgJBZ0x"
            }
          ]
        },
        "geo": {},
        "id": "2049048427313746179",
        "lang": "zh",
        "note_tweet": {
          "entities": {}
        },
        "possibly_sensitive": false,
        "public_metrics": {
          "bookmark_count": 0,
          "impression_count": 78,
          "like_count": 3,
          "quote_count": 0,
          "reply_count": 1,
          "retweet_count": 0
        },
        "referenced_tweets": [
          {
            "id": "2049046973068820873",
            "type": "quoted"
          }
        ],
        "reply_settings": "everyone",
        "text": "那些骂我的人都去死吧\n那些会说我丑的人真的是瞎了你们的狗眼\n老娘活在这个世界上除了照顾好我爸妈，爱护好我爱的人就没有什么需要我来承担的了，至于其他人，愿意和我做朋友的我很感谢，对我有敌意的那你就最好别出现在我眼前，我是真的会把你嘴给你撕烂\n谁他妈都别想限制我\n我会永远好好活着爱我自己 https://t.co/9x7kgJBZ0x"
      }
    ],
    "users": [
      {
        "created_at": "2022-04-03T02:43:33.000Z",
        "description": "你好～ 可以叫我小雫！希望被称作She/Her✨喜欢cos编曲画画💻账号纯绿日常向🏠我终生的爱人然然@dexy0306 是纯爱哦❤️B站6.7w粉同名 混眼熟了会回fo 🥳 祝你生活愉快～☀️10r任意平台公益捐款可加粉丝群",
        "entities": {
          "description": {
            "mentions": [
              {
                "end": 59,
                "start": 50,
                "username": "dexy0306"
              }
            ]
          }
        },
        "id": "1510447851507261445",
        "location": "然然的心里",
        "name": "星野雫丶Shizuku✨",
        "pinned_tweet_id": "1994637461843317173",
        "profile_image_url": "https://pbs.twimg.com/profile_images/1981816759138033665/JwkHNEt6_normal.jpg",
        "protected": false,
        "public_metrics": {
          "followers_count": 22903,
          "following_count": 1051,
          "like_count": 2009,
          "listed_count": 66,
          "media_count": 394,
          "tweet_count": 2063
        },
        "username": "LanziiLove",
        "verified": false
      },
      {
        "created_at": "2024-03-11T04:12:28.000Z",
        "description": "一只笨笨的邪恶小魅魔｜可以叫我小梅，或者梅子干也行｜很喜欢很喜欢的酸汤面姐姐大人@wang3289 ｜有点腹黑毒舌，但是很好相处，想认识好多好多朋友｜目前精神状态有点差，但是在努力克服啦｜最后……这里有提问箱可以问小梅任何问题哦～⬇️",
        "entities": {
          "description": {
            "mentions": [
              {
                "end": 49,
                "start": 40,
                "username": "wang3289"
              }
            ]
          },
          "url": {
            "urls": [
              {
                "display_url": "ngl.link/meviuslx_xl",
                "end": 23,
                "expanded_url": "https://ngl.link/meviuslx_xl",
                "start": 0,
                "url": "https://t.co/yK6TFzsZWk"
              }
            ]
          }
        },
        "id": "1767040816986656768",
        "location": "魔王城",
        "name": "ℳℯ𝓋𝒾𝓊𝓈",
        "pinned_tweet_id": "2009992139284066816",
        "profile_image_url": "https://pbs.twimg.com/profile_images/1957098651299581952/LUPlmVG6_normal.jpg",
        "protected": false,
        "public_metrics": {
          "followers_count": 12705,
          "following_count": 1046,
          "like_count": 18300,
          "listed_count": 29,
          "media_count": 1044,
          "tweet_count": 8525
        },
        "url": "https://t.co/yK6TFzsZWk",
        "username": "MeviuslX_Xl",
        "verified": false
      }
    ]
  }
}